morphsnakes.py
morphsnakes-2.0.1.dist-info/DESCRIPTION.rst
morphsnakes-2.0.1.dist-info/METADATA
morphsnakes-2.0.1.dist-info/RECORD
morphsnakes-2.0.1.dist-info/WHEEL
morphsnakes-2.0.1.dist-info/metadata.json
morphsnakes-2.0.1.dist-info/top_level.txt
